pyjoin/__init__.py
python_join_api-0.0.9.dist-info/LICENSE.txt
python_join_api-0.0.9.dist-info/METADATA
python_join_api-0.0.9.dist-info/WHEEL
python_join_api-0.0.9.dist-info/top_level.txt
python_join_api-0.0.9.dist-info/zip-safe
python_join_api-0.0.9.dist-info/RECORD
