Metadata-Version: 2.1
Name: python-join-api
Version: 0.0.9
Summary: Python API for interacting with Join by joaoapps.
Home-page: https://github.com/nkgilley/python-join-api
Author: Nolan Gilley
Author-email: nkgilley@gmail.com
License: MIT
Platform: UNKNOWN
Requires-Dist: requests (>=2.0)
Requires-Dist: flask (>=1.1.2)
